llm_template/__init__.py
llm_template/base_generator.py
llm_template/generator.py
llm_template/json_convertor.py
llm_template/stopping_criteria.py
llm_template-0.1.0.dist-info/LICENSE
llm_template-0.1.0.dist-info/METADATA
llm_template-0.1.0.dist-info/WHEEL
llm_template-0.1.0.dist-info/top_level.txt
llm_template-0.1.0.dist-info/RECORD
