Metadata-Version: 2.1
Name: llm-template
Version: 0.1.0
Summary: Package designed to simplify the concept of getting structured output from LLMs
Home-page: https://github.com/vection/llm_template
Author: Aviv Harazi
Author-email: avivzx@gmail.com
License: UNKNOWN
Platform: UNKNOWN
Classifier: Programming Language :: Python :: 3
Classifier: License :: OSI Approved :: MIT License
Classifier: Operating System :: OS Independent
Requires-Python: >=3.9
License-File: LICENSE
Requires-Dist: transformers (==4.41.1)
Requires-Dist: torch (==2.2.1)
